HISTORY.txt
LICENSE.txt
MANIFEST.in
README.md
setup.cfg
setup.py
sparc/__init__.py
sparc.logging.egg-info/PKG-INFO
sparc.logging.egg-info/SOURCES.txt
sparc.logging.egg-info/dependency_links.txt
sparc.logging.egg-info/entry_points.txt
sparc.logging.egg-info/namespace_packages.txt
sparc.logging.egg-info/not-zip-safe
sparc.logging.egg-info/requires.txt
sparc.logging.egg-info/top_level.txt
sparc/logging/__init__.py